{
  "color-primary-100": "#FEFEFB",
  "color-primary-200": "#FEFDF7",
  "color-primary-300": "#FDFBF2",
  "color-primary-400": "#FBF8ED",
  "color-primary-500": "#F9F5E7",
  "color-primary-600": "#D6CBA8",
  "color-primary-700": "#B3A274",
  "color-primary-800": "#907B49",
  "color-primary-900": "#775F2C",
  "color-success-100": "#E2FDD2",
  "color-success-200": "#BFFCA6",
  "color-success-300": "#92F679",
  "color-success-400": "#68EC56",
  "color-success-500": "#29e123",
  "color-success-600": "#19C122",
  "color-success-700": "#11A225",
  "color-success-800": "#0B8225",
  "color-success-900": "#066C25",
  "color-info-100": "#E4E5FD",
  "color-info-200": "#C9CBFC",
  "color-info-300": "#ACAEF6",
  "color-info-400": "#9497EE",
  "color-info-500": "#7174e4",
  "color-info-600": "#5255C4",
  "color-info-700": "#383BA4",
  "color-info-800": "#242584",
  "color-info-900": "#15176D",
  "color-warning-100": "#FCFECF",
  "color-warning-200": "#FAFEA1",
  "color-warning-300": "#F5FC71",
  "color-warning-400": "#F0F94E",
  "color-warning-500": "#e9f615",
  "color-warning-600": "#C7D30F",
  "color-warning-700": "#A5B10A",
  "color-warning-800": "#848E06",
  "color-warning-900": "#6C7604",
  "color-danger-100": "#FDE8D2",
  "color-danger-200": "#FCCBA6",
  "color-danger-300": "#F8A579",
  "color-danger-400": "#F18156",
  "color-danger-500": "#e84a22",
  "color-danger-600": "#C72F18",
  "color-danger-700": "#A71911",
  "color-danger-800": "#860A0D",
  "color-danger-900": "#6F0610"
}